flowde/__init__.py
flowde/__main__.py
flowde/cli.py
flowde/func.py
flowde-0.0.6.dist-info/LICENSE
flowde-0.0.6.dist-info/METADATA
flowde-0.0.6.dist-info/WHEEL
flowde-0.0.6.dist-info/entry_points.txt
flowde-0.0.6.dist-info/top_level.txt
flowde-0.0.6.dist-info/RECORD
