Metadata-Version: 2.1
Name: flowde
Version: 0.0.6
Summary: Flowde, a simple library made to help you in utilities
Author: General Zero
Author-email: General Zero <GeneralZeroCosmo@gmail.com>
License: Apache Software License 2.0
Project-URL: Documentation, https://github.com/General-Zero/flowde-documentation
Keywords: flowde,Flowde,FLOWDE,Utilities,Utility,utilities,utility
Classifier: Intended Audience :: Developers
Classifier: Natural Language :: English
Classifier: Programming Language :: Python :: 3
Classifier: Programming Language :: Python :: 3.8
Classifier: Programming Language :: Python :: 3.11
Classifier: Development Status :: 3 - Alpha
Classifier: License :: OSI Approved :: Apache Software License
Classifier: Topic :: Utilities
Requires-Python: >=3.8
License-File: LICENSE
Requires-Dist: requests
Requires-Dist: colorama
Requires-Dist: flask
